pycasestyle/__init__.py
pycasestyle/camelcase.py
pycasestyle/kebabcase.py
pycasestyle/pascalcase.py
pycasestyle/snakecase.py
pycasestyle/abstract/__init__.py
pycasestyle/abstract/case.py
pycasestyle/libs/__init__.py
pycasestyle/libs/string.py
pycasestyle-0.1.4.dist-info/LICENSE
pycasestyle-0.1.4.dist-info/METADATA
pycasestyle-0.1.4.dist-info/WHEEL
pycasestyle-0.1.4.dist-info/top_level.txt
pycasestyle-0.1.4.dist-info/RECORD
