Metadata-Version: 2.1
Name: pycasestyle
Version: 0.1.4
Summary: A simple python lib to convert string and dict keys to camelcase, pascal case, kebab case and snake case.
Home-page: https://github.com/preduus/pycasestyle
Author: Pedro Rodrigues
Author-email: pedrota.rodrigues@gmail.com
License: Apache License 2.0
Keywords: pycasestyle,camelcase,snakecase,pascal case,kebab case,dict key case,string case
Classifier: Development Status :: 4 - Beta
Classifier: Intended Audience :: Developers
Classifier: License :: OSI Approved :: Apache Software License
Classifier: Programming Language :: Python
Classifier: Programming Language :: Python :: 3
Classifier: Programming Language :: Python :: 3.4
Classifier: Programming Language :: Python :: 3.5
Classifier: Programming Language :: Python :: 3.6
Classifier: Programming Language :: Python :: 3.7
Classifier: Programming Language :: Python :: 3.8
Classifier: Programming Language :: Python :: 3.9
Classifier: Programming Language :: Python :: 3.10
Requires-Python: >=3
License-File: LICENSE
Requires-Dist: Unidecode ==1.3.8
